cycarla_backend/__init__.py
cycarla_backend/ble_utils.py
cycarla_backend/carla_control.py
cycarla_backend/filters.py
cycarla_backend/gpx.py
cycarla_backend/main.py
cycarla_backend/profile.html
cycarla_backend/profile.json
cycarla_backend/pycycling_input.py
cycarla_backend/STRAVA_HOWTO.md
cycarla_backend-0.1.12.dist-info/entry_points.txt
cycarla_backend-0.1.12.dist-info/METADATA
cycarla_backend-0.1.12.dist-info/WHEEL
cycarla_backend-0.1.12.dist-info/RECORD
