Metadata-Version: 2.1
Name: cycarla-backend
Version: 0.1.12
Summary: Backend for Cycarla
Author: tensorturtle
Author-email: tensorturtle@gmail.com
Requires-Python: >=3.10.0,<3.11.0
Classifier: Programming Language :: Python :: 3
Classifier: Programming Language :: Python :: 3.10
Requires-Dist: bleak (>=0.21.1,<0.22.0)
Requires-Dist: carla (>=0.9.15,<0.10.0)
Requires-Dist: flask (>=3.0.0,<4.0.0)
Requires-Dist: flask-cors (>=4.0.0,<5.0.0)
Requires-Dist: flask-socketio (>=5.3.6,<6.0.0)
Requires-Dist: numpy (==1.22.0)
Requires-Dist: opencv-python (>=4.8.1.78,<5.0.0.0)
Requires-Dist: pycycling (>=0.3.3,<0.4.0)
Requires-Dist: pygame (>=2.1.2,<3.0.0)
